standardnotes_fs/__init__.py
standardnotes_fs/__main__.py
standardnotes_fs/api.py
standardnotes_fs/crypt.py
standardnotes_fs/itemmanager.py
standardnotes_fs/sn_fuse.py
standardnotes_fs/standardnotes_fs.py
standardnotes_fs-0.0.2.dist-info/METADATA
standardnotes_fs-0.0.2.dist-info/RECORD
standardnotes_fs-0.0.2.dist-info/WHEEL
standardnotes_fs-0.0.2.dist-info/entry_points.txt
standardnotes_fs-0.0.2.dist-info/top_level.txt
