Metadata-Version: 2.1
Name: standardnotes-fs
Version: 0.0.2
Summary: Mount your Standard Notes as a filesystem.
Home-page: https://github.com/tannercollin/standardnotes-fs
Author: Tanner Collin
Author-email: pypi@tannercollin.com
Maintainer: Tanner Collin
Maintainer-email: pypi@tannercollin.com
License: GPLv3
Keywords: standard-notes standard-file fuse standardnotes secure encrypted notes fusepy
Platform: UNKNOWN
Classifier: License :: OSI Approved :: GNU General Public License v3 (GPLv3)
Classifier: Natural Language :: English
Classifier: Operating System :: MacOS
Classifier: Operating System :: POSIX :: Linux
Classifier: Operating System :: Unix
Classifier: Programming Language :: Python :: 3
Classifier: Programming Language :: Python :: 3.4
Classifier: Programming Language :: Python :: 3.5
Classifier: Programming Language :: Python :: 3.6
Classifier: Topic :: System :: Filesystems
Classifier: Topic :: Text Editors :: Text Processing
Requires-Python: >=3
Requires-Dist: appdirs
Requires-Dist: fusepy
Requires-Dist: iso8601
Requires-Dist: pycryptodome
Requires-Dist: requests
